quine_wasm32/__init__.py
quine_wasm32-0.0.0.dist-info/METADATA
quine_wasm32-0.0.0.dist-info/WHEEL
quine_wasm32-0.0.0.dist-info/RECORD
