Metadata-Version: 2.3
Name: quine-wasm32
Version: 0.0.0
Summary: Dummy release for name reservation.
License: AGPL-3.0-or-later
Author: Hendrik M Halkow
Author-email: hendrik@halkow.com
Requires-Python: >=3.13
Classifier: License :: OSI Approved :: GNU Affero General Public License v3 or later (AGPLv3+)
Classifier: Programming Language :: Python :: 3
Classifier: Programming Language :: Python :: 3.13
